[{"id":1,"assembler":"MEGAHIT","version":"1.2.9","container":"cimendes/megahit-assembler:1.2.9-1","avgTime":"00:27:57","cpus":43.37,"max_rss":"8.5GB","avgRead":"47.3GB","avgWrite":"17.8GB"},{"id":2,"assembler":"SKESA","version":"2.5.0","container":"cimendes/skesa:2.5.0-1","avgTime":"00:20:37","cpus":22.93,"max_rss":"21.0GB","avgRead":"1.7GB","avgWrite":"18MB"},{"id":3,"assembler":"SPADES","version":"3.15.3","container":"cimendes/spades:3.15.3-1","avgTime":"01:04:18","cpus":90.42,"max_rss":"8.4GB","avgRead":"33.1GB","avgWrite":"50.2GB"},{"id":4,"assembler":"METASPADES","version":"3.15.3","container":"cimendes/spades:3.15.3-1","avgTime":"01:12:14","cpus":100.5,"max_rss":"8.3GB","avgRead":"41.5GB","avgWrite":"40.3GB"},{"id":5,"assembler":"IDBA","version":"","container":"cimendes/idba:1.1.3-1","avgTime":"00:42:30","cpus":71.45,"max_rss":"27.7GB","avgRead":"12.1GB","avgWrite":"4.0GB"},{"id":6,"assembler":"GATBMINIAPIPELINE","version":"","container":"cimendes/gatb-minia-pipeline:31.07.2020-1","avgTime":"01:15:55","cpus":143.08,"max_rss":"7.4GB","avgRead":"101.3GB","avgWrite":"29.7GB"},{"id":7,"assembler":"UNICYCLER","version":"0.4.9","container":"cimendes/unicycler:0.4.9-1","avgTime":"10:53:08","cpus":333.94,"max_rss":"23.1GB","avgRead":"104.2GB","avgWrite":"279.8GB"}]